odoo/addons/l10n_it_pos_fatturapa/README.rst
odoo/addons/l10n_it_pos_fatturapa/__init__.py
odoo/addons/l10n_it_pos_fatturapa/__manifest__.py
odoo/addons/l10n_it_pos_fatturapa/i18n/it.po
odoo/addons/l10n_it_pos_fatturapa/i18n/l10n_it_pos_fatturapa.pot
odoo/addons/l10n_it_pos_fatturapa/models/__init__.py
odoo/addons/l10n_it_pos_fatturapa/models/res_partner.py
odoo/addons/l10n_it_pos_fatturapa/readme/CONTRIBUTORS.rst
odoo/addons/l10n_it_pos_fatturapa/readme/DESCRIPTION.rst
odoo/addons/l10n_it_pos_fatturapa/static/description/icon.png
odoo/addons/l10n_it_pos_fatturapa/static/description/index.html
odoo/addons/l10n_it_pos_fatturapa/static/src/js/ClientDetailsEdit.js
odoo/addons/l10n_it_pos_fatturapa/static/src/js/models.js
odoo/addons/l10n_it_pos_fatturapa/static/src/xml/pos_dump.xml
odoo/addons/l10n_it_pos_fatturapa/views/assets.xml
odoo14_addon_l10n_it_pos_fatturapa-14.0.1.0.1.dev5.dist-info/METADATA
odoo14_addon_l10n_it_pos_fatturapa-14.0.1.0.1.dev5.dist-info/WHEEL
odoo14_addon_l10n_it_pos_fatturapa-14.0.1.0.1.dev5.dist-info/top_level.txt
odoo14_addon_l10n_it_pos_fatturapa-14.0.1.0.1.dev5.dist-info/RECORD
