Metadata-Version: 2.1
Name: odoo14-addon-l10n-it-pos-fatturapa
Version: 14.0.1.0.1.dev5
Summary: Gestione dati fattura elettronica del cliente all'internodell'interfaccia del POS
Home-page: https://github.com/OCA/l10n-italy
Author: Odoo Community Association (OCA)
Author-email: support@odoo-community.org
License: AGPL-3
Platform: UNKNOWN
Classifier: Programming Language :: Python
Classifier: Framework :: Odoo
Classifier: Framework :: Odoo :: 14.0
Classifier: License :: OSI Approved :: GNU Affero General Public License v3
Classifier: Development Status :: 4 - Beta
Requires-Python: >=3.6
Requires-Dist: odoo14-addon-l10n-it-fatturapa
Requires-Dist: odoo14-addon-l10n-it-pos-fiscalcode
Requires-Dist: odoo14-addon-pos-partner-firstname
Requires-Dist: odoo <14.1dev,>=14.0a
